[
    {
        "type":2,
        "data":[0,0,242,143,255,0],
        "color":[255,255,255,128],
        "score":0.5272949207360677
    },
    {
        "type":2,
        "data":[0,0,255,143,0,143],
        "color":[252,235,223,128],
        "score":0.32938776040576684
    },
    {
        "type":2,
        "data":[0,0,255,143,255,0],
        "color":[255,232,207,128],
        "score":0.24384472329650175
    },
    {
        "type":2,
        "data":[255,90,0,9,126,155],
        "color":[157,137,126,128],
        "score":0.21514337154622318
    },
    {
        "type":2,
        "data":[0,143,255,143,0,0],
        "color":[124,118,114,128],
        "score":0.17907238713115484
    },
    {
        "type":2,
        "data":[0,86,63,48,67,143],
        "color":[4,21,33,128],
        "score":0.16913228607487896
    },
    {
        "type":2,
        "data":[88,143,178,143,158,115],
        "color":[0,0,0,128],
        "score":0.15763454808822833
    },
    {
        "type":2,
        "data":[87,143,255,0,40,0],
        "color":[209,183,166,128],
        "score":0.14294489888244513
    },
    {
        "type":2,
        "data":[34,32,0,135,0,24],
        "color":[217,196,177,128],
        "score":0.13695852746886966
    },
    {
        "type":2,
        "data":[99,143,181,143,150,116],
        "color":[0,0,0,128],
        "score":0.13422070335448588
    },
    {
        "type":2,
        "data":[123,116,255,0,255,143],
        "color":[200,181,175,128],
        "score":0.11846802934148522
    },
    {
        "type":2,
        "data":[255,0,0,28,0,0],
        "color":[233,205,185,128],
        "score":0.1147144928477415
    },
    {
        "type":2,
        "data":[170,76,115,19,95,143],
        "color":[113,102,93,128],
        "score":0.1079621627781434
    },
    {
        "type":2,
        "data":[105,143,131,99,0,143],
        "color":[149,146,143,128],
        "score":0.1044158569846248
    },
    {
        "type":2,
        "data":[175,143,255,19,255,143],
        "color":[162,153,149,128],
        "score":0.0998830003044557
    },
    {
        "type":2,
        "data":[255,6,178,143,141,0],
        "color":[222,199,184,128],
        "score":0.09540217182778228
    },
    {
        "type":2,
        "data":[78,143,0,143,0,92],
        "color":[105,108,109,128],
        "score":0.09270836933215772
    },
    {
        "type":2,
        "data":[74,121,42,19,14,121],
        "color":[39,49,54,128],
        "score":0.08937054426109783
    },
    {
        "type":2,
        "data":[70,79,10,83,44,23],
        "color":[93,91,89,128],
        "score":0.08785878136838177
    },
    {
        "type":2,
        "data":[0,36,0,82,49,31],
        "color":[205,187,170,128],
        "score":0.08657500441160242
    },
    {
        "type":2,
        "data":[201,36,255,77,255,42],
        "color":[253,247,240,128],
        "score":0.08382773035795793
    },
    {
        "type":2,
        "data":[33,136,2,111,0,57],
        "color":[171,157,146,128],
        "score":0.0828150590471534
    },
    {
        "type":2,
        "data":[186,71,248,30,224,66],
        "color":[231,220,212,128],
        "score":0.08252661926666296
    },
    {
        "type":2,
        "data":[81,117,23,57,11,84],
        "color":[46,56,62,128],
        "score":0.08186536950478725
    },
    {
        "type":2,
        "data":[252,143,255,117,221,82],
        "color":[117,113,110,128],
        "score":0.08115253206290653
    },
    {
        "type":2,
        "data":[215,76,231,103,189,100],
        "color":[124,111,105,128],
        "score":0.08007500924012574
    },
    {
        "type":2,
        "data":[43,0,84,100,133,0],
        "color":[224,202,187,128],
        "score":0.07691414756657397
    },
    {
        "type":2,
        "data":[48,29,38,12,15,37],
        "color":[123,114,96,128],
        "score":0.0761422965018068
    },
    {
        "type":2,
        "data":[231,143,211,135,219,143],
        "color":[255,255,255,128],
        "score":0.07541074414974724
    },
    {
        "type":2,
        "data":[124,143,172,143,153,111],
        "color":[0,0,0,128],
        "score":0.0745019622305093
    },
    {
        "type":2,
        "data":[63,51,31,48,36,12],
        "color":[132,122,107,128],
        "score":0.07423805289503883
    },
    {
        "type":2,
        "data":[145,118,189,120,184,88],
        "color":[215,199,193,128],
        "score":0.0734398503381774
    },
    {
        "type":2,
        "data":[160,57,126,5,101,43],
        "color":[171,152,139,128],
        "score":0.07275341992714296
    },
    {
        "type":2,
        "data":[101,97,159,110,162,78],
        "color":[119,101,91,128],
        "score":0.07182496741975626
    },
    {
        "type":2,
        "data":[64,38,20,0,255,18],
        "color":[219,196,179,128],
        "score":0.07117182977668166
    },
    {
        "type":2,
        "data":[240,143,264,143,230,124],
        "color":[92,93,98,128],
        "score":0.07061797166472551
    },
    {
        "type":2,
        "data":[35,83,18,113,65,120],
        "color":[0,15,27,128],
        "score":0.06926211918196115
    },
    {
        "type":2,
        "data":[105,86,40,143,104,143],
        "color":[154,146,140,128],
        "score":0.06829093980700858
    },
    {
        "type":2,
        "data":[63,121,143,101,139,122],
        "color":[176,162,152,128],
        "score":0.0676563077992824
    },
    {
        "type":2,
        "data":[0,15,0,28,38,33],
        "color":[109,98,82,128],
        "score":0.06683750109697716
    },
    {
        "type":2,
        "data":[209,143,178,143,216,111],
        "color":[134,128,125,128],
        "score":0.06648310511429044
    },
    {
        "type":2,
        "data":[151,36,108,61,142,77],
        "color":[126,110,98,128],
        "score":0.0660265928016165
    },
    {
        "type":2,
        "data":[67,85,63,118,82,105],
        "color":[133,121,114,128],
        "score":0.06556969518818452
    },
    {
        "type":2,
        "data":[228,143,255,103,243,60],
        "color":[164,151,146,128],
        "score":0.06520453464195286
    },
    {
        "type":2,
        "data":[221,106,165,123,183,143],
        "color":[179,165,159,128],
        "score":0.06491215758562428
    },
    {
        "type":2,
        "data":[255,75,212,71,236,112],
        "color":[156,141,132,128],
        "score":0.06460753242484407
    },
    {
        "type":2,
        "data":[88,143,0,143,0,111],
        "color":[116,117,117,128],
        "score":0.06407283694001666
    },
    {
        "type":2,
        "data":[60,0,17,27,0,0],
        "color":[206,175,154,128],
        "score":0.06359959598038728
    },
    {
        "type":2,
        "data":[177,41,255,1,200,65],
        "color":[192,161,144,128],
        "score":0.06261813380836513
    },
    {
        "type":2,
        "data":[134,0,135,39,244,0],
        "color":[229,208,193,128],
        "score":0.06199432190025731
    },
    {
        "type":2,
        "data":[201,57,211,56,180,44],
        "color":[132,103,85,128],
        "score":0.06162646316957403
    },
    {
        "type":2,
        "data":[206,103,227,101,223,99],
        "color":[54,52,51,128],
        "score":0.061402884144078525
    },
    {
        "type":2,
        "data":[255,49,208,1,255,0],
        "color":[203,169,148,128],
        "score":0.06075874126875108
    },
    {
        "type":2,
        "data":[110,21,104,80,135,22],
        "color":[157,142,129,128],
        "score":0.06037329752071853
    },
    {
        "type":2,
        "data":[130,43,178,28,194,73],
        "color":[209,187,174,128],
        "score":0.060140261119252615
    },
    {
        "type":2,
        "data":[83,18,70,87,108,112],
        "color":[198,181,169,128],
        "score":0.05968465427288836
    },
    {
        "type":2,
        "data":[186,98,173,102,186,103],
        "color":[251,238,231,128],
        "score":0.05961602815190091
    },
    {
        "type":2,
        "data":[255,47,252,34,242,33],
        "color":[137,110,109,128],
        "score":0.05942106623815079
    },
    {
        "type":2,
        "data":[224,123,255,128,255,107],
        "color":[132,126,123,128],
        "score":0.05923034723364434
    },
    {
        "type":2,
        "data":[31,122,20,109,43,115],
        "color":[0,0,7,128],
        "score":0.05872348852513723
    },
    {
        "type":2,
        "data":[82,110,53,126,47,120],
        "color":[4,14,16,128],
        "score":0.058309013876158826
    },
    {
        "type":2,
        "data":[0,22,37,51,0,66],
        "color":[203,182,165,128],
        "score":0.05792359604567388
    },
    {
        "type":2,
        "data":[135,101,111,129,136,122],
        "color":[177,166,158,128],
        "score":0.057691900689549144
    },
    {
        "type":2,
        "data":[106,143,158,126,112,128],
        "color":[0,0,0,128],
        "score":0.05669362094469055
    },
    {
        "type":2,
        "data":[68,109,93,87,74,70],
        "color":[183,169,159,128],
        "score":0.05643835295988764
    },
    {
        "type":2,
        "data":[255,103,255,100,243,103],
        "color":[255,255,255,128],
        "score":0.056121720138688214
    },
    {
        "type":2,
        "data":[249,99,218,133,211,110],
        "color":[203,189,186,128],
        "score":0.05582287388987263
    },
    {
        "type":2,
        "data":[10,80,67,118,55,72],
        "color":[44,54,62,128],
        "score":0.055636977471404364
    },
    {
        "type":2,
        "data":[237,132,234,143,210,100],
        "color":[157,145,145,128],
        "score":0.055501138390641164
    },
    {
        "type":2,
        "data":[119,25,80,71,43,16],
        "color":[210,188,173,128],
        "score":0.05532701910413818
    },
    {
        "type":2,
        "data":[255,128,255,143,228,143],
        "color":[104,106,109,128],
        "score":0.055124827203063706
    },
    {
        "type":2,
        "data":[196,125,189,95,237,62],
        "color":[175,158,148,128],
        "score":0.05495266702474363
    },
    {
        "type":2,
        "data":[114,113,98,74,139,99],
        "color":[119,103,93,128],
        "score":0.054614203717628804
    },
    {
        "type":2,
        "data":[102,143,153,119,179,143],
        "color":[3,0,0,128],
        "score":0.05421487693893641
    },
    {
        "type":2,
        "data":[33,66,73,70,33,37],
        "color":[94,91,89,128],
        "score":0.054042858448161264
    },
    {
        "type":2,
        "data":[146,121,178,143,172,132],
        "color":[19,10,5,128],
        "score":0.05382494278539071
    },
    {
        "type":2,
        "data":[249,41,215,72,208,34],
        "color":[230,222,215,128],
        "score":0.05356305140123688
    },
    {
        "type":2,
        "data":[21,59,15,112,12,64],
        "color":[138,135,123,128],
        "score":0.053151828798792725
    },
    {
        "type":2,
        "data":[221,141,166,128,150,109],
        "color":[170,155,150,128],
        "score":0.05294033133894951
    },
    {
        "type":2,
        "data":[107,61,163,95,152,115],
        "color":[134,118,109,128],
        "score":0.05276006412426272
    },
    {
        "type":2,
        "data":[255,112,216,87,255,135],
        "color":[144,136,130,128],
        "score":0.05267864219658051
    },
    {
        "type":2,
        "data":[146,79,147,91,127,70],
        "color":[173,160,157,128],
        "score":0.05253418656483166
    },
    {
        "type":2,
        "data":[13,130,47,116,54,143],
        "color":[135,132,128,128],
        "score":0.05206733843048466
    },
    {
        "type":2,
        "data":[19,26,39,23,7,50],
        "color":[140,134,121,128],
        "score":0.05191774908879789
    },
    {
        "type":2,
        "data":[70,82,69,105,60,110],
        "color":[118,105,98,128],
        "score":0.05168048137876861
    },
    {
        "type":2,
        "data":[106,116,88,143,117,128],
        "color":[130,125,121,128],
        "score":0.05149653218108332
    },
    {
        "type":2,
        "data":[0,19,23,26,18,32],
        "color":[102,96,84,128],
        "score":0.0513456038577075
    },
    {
        "type":2,
        "data":[214,110,229,112,237,114],
        "color":[255,255,255,128],
        "score":0.05118188562241336
    },
    {
        "type":2,
        "data":[244,100,255,75,255,101],
        "color":[182,165,157,128],
        "score":0.05106789591192731
    },
    {
        "type":2,
        "data":[119,34,125,2,137,3],
        "color":[184,152,135,128],
        "score":0.050865248652044275
    },
    {
        "type":2,
        "data":[0,0,49,0,23,24],
        "color":[206,180,162,128],
        "score":0.05076983047244887
    },
    {
        "type":2,
        "data":[135,82,127,20,147,70],
        "color":[131,118,108,128],
        "score":0.05061719171439145
    },
    {
        "type":2,
        "data":[227,143,212,136,218,136],
        "color":[255,255,252,128],
        "score":0.05045451023425622
    },
    {
        "type":2,
        "data":[17,117,0,99,17,89],
        "color":[172,158,148,128],
        "score":0.05024499529222028
    },
    {
        "type":2,
        "data":[33,53,65,85,10,85],
        "color":[62,69,74,128],
        "score":0.050043104691088316
    },
    {
        "type":2,
        "data":[142,33,165,77,136,54],
        "color":[154,135,122,128],
        "score":0.04990903173095296
    },
    {
        "type":2,
        "data":[24,115,71,116,19,77],
        "color":[25,39,47,128],
        "score":0.049757906693872964
    },
    {
        "type":2,
        "data":[188,99,196,92,255,90],
        "color":[153,140,133,128],
        "score":0.049704514467639
    },
    {
        "type":2,
        "data":[46,0,127,0,100,21],
        "color":[232,213,197,128],
        "score":0.04952179173980921
    },
    {
        "type":2,
        "data":[255,44,255,0,239,0],
        "color":[194,166,147,128],
        "score":0.04941214720573492
    },
    {
        "type":2,
        "data":[62,43,33,18,25,29],
        "color":[132,123,110,128],
        "score":0.0493657441653318
    },
    {
        "type":2,
        "data":[220,0,146,0,205,30],
        "color":[226,205,189,128],
        "score":0.04926666618732982
    },
    {
        "type":2,
        "data":[160,120,231,63,168,50],
        "color":[207,189,177,128],
        "score":0.04900728330906868
    },
    {
        "type":2,
        "data":[213,33,197,36,246,33],
        "color":[155,123,115,128],
        "score":0.048758950276596866
    },
    {
        "type":2,
        "data":[108,12,180,51,204,14],
        "color":[218,197,181,128],
        "score":0.048613208258919245
    },
    {
        "type":2,
        "data":[255,82,234,39,255,50],
        "color":[227,222,215,128],
        "score":0.0484608119917207
    },
    {
        "type":2,
        "data":[136,53,111,85,100,69],
        "color":[122,107,96,128],
        "score":0.04829619003314565
    },
    {
        "type":2,
        "data":[108,101,128,64,134,71],
        "color":[171,155,145,128],
        "score":0.0481298544030081
    },
    {
        "type":2,
        "data":[208,83,165,100,160,65],
        "color":[198,179,169,128],
        "score":0.04804118800591202
    },
    {
        "type":2,
        "data":[106,87,151,100,108,107],
        "color":[118,103,94,128],
        "score":0.04793729710008628
    },
    {
        "type":2,
        "data":[185,143,218,143,164,125],
        "color":[138,131,129,128],
        "score":0.04782473527527313
    },
    {
        "type":2,
        "data":[229,141,218,137,245,128],
        "color":[170,157,159,128],
        "score":0.04776836799719884
    },
    {
        "type":2,
        "data":[22,43,24,27,38,38],
        "color":[193,181,166,128],
        "score":0.04768801767168133
    },
    {
        "type":2,
        "data":[210,2,137,37,130,18],
        "color":[225,206,190,128],
        "score":0.04762592671543207
    },
    {
        "type":2,
        "data":[65,71,60,90,60,59],
        "color":[64,65,71,128],
        "score":0.047575581804009205
    },
    {
        "type":2,
        "data":[205,143,220,110,204,115],
        "color":[142,132,128,128],
        "score":0.04742828807359349
    },
    {
        "type":2,
        "data":[47,120,45,117,33,125],
        "color":[148,143,136,128],
        "score":0.047367664345494595
    },
    {
        "type":2,
        "data":[0,143,26,143,0,105],
        "color":[109,109,107,128],
        "score":0.047242489214222784
    },
    {
        "type":2,
        "data":[26,43,0,78,1,27],
        "color":[198,180,165,128],
        "score":0.04718352771794629
    },
    {
        "type":2,
        "data":[117,109,72,95,78,120],
        "color":[156,144,137,128],
        "score":0.04694651691888296
    },
    {
        "type":2,
        "data":[129,12,95,86,133,32],
        "color":[163,149,137,128],
        "score":0.04686496450166615
    },
    {
        "type":2,
        "data":[213,110,179,121,165,109],
        "color":[210,194,187,128],
        "score":0.04678548355565177
    },
    {
        "type":2,
        "data":[188,28,216,54,192,8],
        "color":[202,177,160,128],
        "score":0.04670030577489211
    },
    {
        "type":2,
        "data":[221,121,218,129,222,130],
        "color":[255,255,254,128],
        "score":0.04653348884997687
    },
    {
        "type":2,
        "data":[33,121,25,115,69,108],
        "color":[9,24,32,128],
        "score":0.04640903578435993
    },
    {
        "type":2,
        "data":[229,49,248,72,240,74],
        "color":[225,215,205,128],
        "score":0.04624930721545588
    },
    {
        "type":2,
        "data":[197,32,231,0,246,32],
        "color":[216,187,168,128],
        "score":0.04612296582672292
    },
    {
        "type":2,
        "data":[18,76,20,112,68,89],
        "color":[40,50,56,128],
        "score":0.04602710190388702
    },
    {
        "type":2,
        "data":[94,99,77,143,62,124],
        "color":[152,143,137,128],
        "score":0.04586029228740701
    },
    {
        "type":2,
        "data":[250,61,247,69,245,64],
        "color":[255,249,243,128],
        "score":0.04583223653197121
    },
    {
        "type":2,
        "data":[15,109,1,128,53,143],
        "color":[126,124,122,128],
        "score":0.04573575069146611
    },
    {
        "type":2,
        "data":[7,121,0,66,19,92],
        "color":[164,150,140,128],
        "score":0.04558571414802434
    },
    {
        "type":2,
        "data":[28,72,17,62,51,39],
        "color":[94,88,85,128],
        "score":0.045485713297389034
    },
    {
        "type":2,
        "data":[205,118,196,126,178,108],
        "color":[175,161,153,128],
        "score":0.04542880384236997
    },
    {
        "type":2,
        "data":[110,89,107,69,131,35],
        "color":[125,110,100,128],
        "score":0.045340276997537794
    },
    {
        "type":2,
        "data":[44,26,55,43,31,54],
        "color":[113,110,99,128],
        "score":0.04529466791512022
    },
    {
        "type":2,
        "data":[87,30,50,37,61,5],
        "color":[222,201,183,128],
        "score":0.04518191649709037
    },
    {
        "type":2,
        "data":[25,31,38,36,30,37],
        "color":[222,213,198,128],
        "score":0.04509378615344341
    },
    {
        "type":2,
        "data":[71,81,122,114,125,125],
        "color":[180,166,155,128],
        "score":0.04500245087656903
    },
    {
        "type":2,
        "data":[106,34,117,50,105,38],
        "color":[146,120,100,128],
        "score":0.044927570187959655
    },
    {
        "type":2,
        "data":[204,73,224,63,224,50],
        "color":[231,220,212,128],
        "score":0.044885777707166945
    },
    {
        "type":2,
        "data":[131,93,159,120,142,90],
        "color":[123,107,99,128],
        "score":0.044819890943022155
    },
    {
        "type":2,
        "data":[42,24,53,24,56,0],
        "color":[202,175,156,128],
        "score":0.0447109936821806
    },
    {
        "type":2,
        "data":[117,85,115,76,123,83],
        "color":[204,187,175,128],
        "score":0.04460877248569664
    },
    {
        "type":2,
        "data":[139,80,150,59,138,54],
        "color":[122,107,97,128],
        "score":0.04454846380781996
    },
    {
        "type":2,
        "data":[234,143,248,143,255,116],
        "color":[123,120,119,128],
        "score":0.04451427612876228
    },
    {
        "type":2,
        "data":[47,122,55,123,62,109],
        "color":[0,5,7,128],
        "score":0.04438883152059508
    },
    {
        "type":2,
        "data":[20,0,0,14,0,0],
        "color":[188,161,142,128],
        "score":0.04430395299796193
    },
    {
        "type":2,
        "data":[75,110,82,116,67,97],
        "color":[120,113,107,128],
        "score":0.04427582147117822
    },
    {
        "type":2,
        "data":[140,23,135,29,131,20],
        "color":[184,169,158,128],
        "score":0.04424151033019527
    },
    {
        "type":2,
        "data":[124,83,143,108,137,83],
        "color":[123,109,97,128],
        "score":0.044208179925035014
    },
    {
        "type":2,
        "data":[125,39,128,47,99,31],
        "color":[170,154,141,128],
        "score":0.04418188769735001
    },
    {
        "type":2,
        "data":[116,72,129,73,143,58],
        "color":[151,137,126,128],
        "score":0.04413900640923454
    },
    {
        "type":2,
        "data":[246,129,232,120,228,111],
        "color":[154,142,137,128],
        "score":0.04410323621225342
    },
    {
        "type":2,
        "data":[0,103,0,117,19,130],
        "color":[131,126,121,128],
        "score":0.04408252670994912
    },
    {
        "type":2,
        "data":[222,95,255,90,227,57],
        "color":[166,151,141,128],
        "score":0.04401804865901175
    },
    {
        "type":2,
        "data":[0,143,17,143,0,124],
        "color":[98,100,101,128],
        "score":0.043982593872731686
    },
    {
        "type":2,
        "data":[216,122,240,134,233,123],
        "color":[148,136,133,128],
        "score":0.043899880595265485
    },
    {
        "type":2,
        "data":[180,143,215,143,206,127],
        "color":[130,126,123,128],
        "score":0.04382885467206553
    },
    {
        "type":2,
        "data":[65,114,81,109,65,106],
        "color":[93,89,86,128],
        "score":0.04377398926864459
    },
    {
        "type":2,
        "data":[51,126,122,117,103,143],
        "color":[145,138,133,128],
        "score":0.04365487269815769
    },
    {
        "type":2,
        "data":[111,99,120,111,129,106],
        "color":[109,94,83,128],
        "score":0.04357814557132398
    },
    {
        "type":2,
        "data":[44,119,70,142,38,118],
        "color":[134,131,127,128],
        "score":0.04352602886553082
    },
    {
        "type":2,
        "data":[69,74,98,27,100,91],
        "color":[197,178,165,128],
        "score":0.04343498540672976
    },
    {
        "type":2,
        "data":[119,35,106,20,104,29],
        "color":[221,199,187,128],
        "score":0.04338007504089873
    },
    {
        "type":2,
        "data":[19,24,2,13,56,0],
        "color":[211,184,165,128],
        "score":0.04335334314712461
    },
    {
        "type":2,
        "data":[32,39,53,41,58,60],
        "color":[105,98,92,128],
        "score":0.043310896113328806
    },
    {
        "type":2,
        "data":[199,87,232,96,203,103],
        "color":[153,140,134,128],
        "score":0.04329065438637838
    },
    {
        "type":2,
        "data":[141,27,138,35,208,32],
        "color":[209,188,174,128],
        "score":0.043255711286978575
    },
    {
        "type":2,
        "data":[78,91,67,104,141,121],
        "color":[166,154,144,128],
        "score":0.0431388384746916
    },
    {
        "type":2,
        "data":[14,76,0,48,0,75],
        "color":[192,174,162,128],
        "score":0.043091377376462216
    },
    {
        "type":2,
        "data":[255,91,249,81,239,54],
        "color":[140,117,104,128],
        "score":0.042926617226044426
    },
    {
        "type":2,
        "data":[34,96,49,116,17,112],
        "color":[15,31,40,128],
        "score":0.04279314260151293
    },
    {
        "type":2,
        "data":[158,113,162,75,144,75],
        "color":[143,122,111,128],
        "score":0.04272432906060143
    },
    {
        "type":2,
        "data":[54,45,37,14,37,21],
        "color":[122,112,99,128],
        "score":0.04267024199941948
    },
    {
        "type":2,
        "data":[170,84,175,79,172,78],
        "color":[255,242,231,128],
        "score":0.04261561641229978
    },
    {
        "type":2,
        "data":[245,94,255,95,252,92],
        "color":[235,225,220,128],
        "score":0.042515433173879194
    },
    {
        "type":2,
        "data":[42,95,10,79,36,71],
        "color":[56,65,70,128],
        "score":0.04247762922054647
    },
    {
        "type":2,
        "data":[174,59,198,79,197,67],
        "color":[230,210,197,128],
        "score":0.04242221598724473
    },
    {
        "type":2,
        "data":[237,59,245,38,207,38],
        "color":[231,223,217,128],
        "score":0.04229915363107508
    },
    {
        "type":2,
        "data":[101,143,96,126,115,127],
        "color":[121,118,115,128],
        "score":0.04224980511957973
    },
    {
        "type":2,
        "data":[220,103,247,93,246,98],
        "color":[129,119,114,128],
        "score":0.04216258828704659
    },
    {
        "type":2,
        "data":[0,11,20,3,14,24],
        "color":[194,168,151,128],
        "score":0.0421320628754186
    },
    {
        "type":2,
        "data":[184,44,204,30,211,58],
        "color":[192,166,151,128],
        "score":0.04205160131317803
    },
    {
        "type":2,
        "data":[255,0,255,36,234,33],
        "color":[195,167,150,128],
        "score":0.0420082287327708
    },
    {
        "type":2,
        "data":[80,143,69,125,111,113],
        "color":[159,149,142,128],
        "score":0.04197293361268905
    },
    {
        "type":2,
        "data":[113,132,108,148,138,122],
        "color":[1,1,0,128],
        "score":0.04176581940466974
    },
    {
        "type":2,
        "data":[42,22,82,53,110,21],
        "color":[212,191,174,128],
        "score":0.0417163974975801
    },
    {
        "type":2,
        "data":[141,49,140,31,155,43],
        "color":[173,153,137,128],
        "score":0.041676516230986775
    },
    {
        "type":2,
        "data":[18,74,20,56,0,84],
        "color":[163,153,141,128],
        "score":0.041571800947217144
    },
    {
        "type":2,
        "data":[24,143,70,126,70,117],
        "color":[125,123,120,128],
        "score":0.04150266361743924
    },
    {
        "type":2,
        "data":[61,40,70,82,53,41],
        "color":[162,131,116,128],
        "score":0.041358928656958255
    },
    {
        "type":2,
        "data":[160,114,165,84,164,121],
        "color":[213,193,184,128],
        "score":0.04130927368370182
    },
    {
        "type":2,
        "data":[91,54,92,50,92,44],
        "color":[150,129,115,128],
        "score":0.04127145026063924
    },
    {
        "type":2,
        "data":[123,85,103,83,106,88],
        "color":[164,148,135,128],
        "score":0.04123732906255642
    },
    {
        "type":2,
        "data":[127,82,153,92,117,97],
        "color":[129,115,105,128],
        "score":0.041219750573282525
    },
    {
        "type":2,
        "data":[78,113,71,93,100,112],
        "color":[151,140,133,128],
        "score":0.04117305617587168
    },
    {
        "type":2,
        "data":[214,93,255,95,255,100],
        "color":[156,144,138,128],
        "score":0.04113361666643924
    },
    {
        "type":2,
        "data":[107,110,99,118,102,91],
        "color":[182,168,157,128],
        "score":0.0411163679785856
    },
    {
        "type":2,
        "data":[190,29,186,43,146,4],
        "color":[221,200,183,128],
        "score":0.04109882403205325
    },
    {
        "type":2,
        "data":[111,81,125,107,111,106],
        "color":[119,104,95,128],
        "score":0.04108226648671717
    },
    {
        "type":2,
        "data":[210,106,196,106,215,105],
        "color":[243,228,224,128],
        "score":0.04096441325444762
    },
    {
        "type":2,
        "data":[114,128,115,108,148,119],
        "color":[167,156,148,128],
        "score":0.04074621037737714
    },
    {
        "type":2,
        "data":[121,25,107,53,127,47],
        "color":[161,147,134,128],
        "score":0.040714176066396705
    },
    {
        "type":2,
        "data":[107,19,150,18,110,20],
        "color":[255,236,212,128],
        "score":0.04057378625136093
    },
    {
        "type":2,
        "data":[184,63,201,59,180,77],
        "color":[200,175,162,128],
        "score":0.04053401452115594
    },
    {
        "type":2,
        "data":[245,28,211,11,246,0],
        "color":[213,185,167,128],
        "score":0.040499254001643004
    },
    {
        "type":2,
        "data":[72,139,73,143,22,143],
        "color":[112,113,114,128],
        "score":0.0404788004987037
    },
    {
        "type":2,
        "data":[231,131,228,133,235,134],
        "color":[255,255,255,128],
        "score":0.04026340558494609
    },
    {
        "type":2,
        "data":[16,123,0,81,18,87],
        "color":[159,146,137,128],
        "score":0.04020163571997805
    },
    {
        "type":2,
        "data":[84,104,56,135,76,126],
        "color":[149,142,136,128],
        "score":0.040175609463810096
    },
    {
        "type":2,
        "data":[220,69,214,43,232,56],
        "color":[230,221,212,128],
        "score":0.04011835283961699
    },
    {
        "type":2,
        "data":[248,13,252,32,224,32],
        "color":[204,176,159,128],
        "score":0.04010538891353855
    },
    {
        "type":2,
        "data":[136,123,113,129,160,115],
        "color":[139,128,122,128],
        "score":0.04001516239015296
    },
    {
        "type":2,
        "data":[192,94,213,75,204,62],
        "color":[201,181,170,128],
        "score":0.03998893652909303
    },
    {
        "type":2,
        "data":[137,88,149,83,145,88],
        "color":[171,164,158,128],
        "score":0.03995921839560942
    },
    {
        "type":2,
        "data":[211,57,196,92,208,51],
        "color":[204,181,168,128],
        "score":0.03993792949439915
    },
    {
        "type":2,
        "data":[54,134,68,125,20,127],
        "color":[126,123,121,128],
        "score":0.03992243572683578
    },
    {
        "type":2,
        "data":[205,29,214,4,204,5],
        "color":[236,219,200,128],
        "score":0.03987631192693594
    },
    {
        "type":2,
        "data":[184,110,205,103,195,98],
        "color":[181,164,159,128],
        "score":0.0398574424046869
    },
    {
        "type":2,
        "data":[42,61,51,74,66,67],
        "color":[74,77,81,128],
        "score":0.039830973921695316
    },
    {
        "type":2,
        "data":[160,111,160,91,161,87],
        "color":[164,140,131,128],
        "score":0.03981550663844253
    },
    {
        "type":2,
        "data":[135,101,148,112,122,112],
        "color":[181,168,156,128],
        "score":0.03974924700385935
    },
    {
        "type":2,
        "data":[210,57,249,54,241,40],
        "color":[225,215,207,128],
        "score":0.03972702914057574
    },
    {
        "type":2,
        "data":[0,0,1,13,18,24],
        "color":[191,165,149,128],
        "score":0.03971314306521664
    },
    {
        "type":2,
        "data":[182,101,172,130,165,126],
        "color":[182,167,160,128],
        "score":0.039637534546862335
    },
    {
        "type":2,
        "data":[195,55,151,55,171,42],
        "color":[213,192,177,128],
        "score":0.03960691288624925
    },
    {
        "type":2,
        "data":[171,93,167,116,162,86],
        "color":[185,169,159,128],
        "score":0.03956648426323238
    },
    {
        "type":2,
        "data":[76,66,67,55,72,73],
        "color":[188,167,155,128],
        "score":0.039544743937083085
    },
    {
        "type":2,
        "data":[131,8,123,11,124,3],
        "color":[167,135,123,128],
        "score":0.03948168067277545
    },
    {
        "type":2,
        "data":[14,31,39,29,6,22],
        "color":[116,108,95,128],
        "score":0.03940267822621463
    },
    {
        "type":2,
        "data":[213,0,209,32,241,0],
        "color":[215,187,169,128],
        "score":0.03937679266822771
    },
    {
        "type":2,
        "data":[255,131,255,143,228,138],
        "color":[114,114,114,128],
        "score":0.039324938609854906
    },
    {
        "type":2,
        "data":[183,138,177,144,198,152],
        "color":[160,152,143,128],
        "score":0.039297913754384614
    },
    {
        "type":2,
        "data":[194,108,181,124,176,115],
        "color":[222,205,198,128],
        "score":0.039264497319824496
    },
    {
        "type":2,
        "data":[168,126,196,120,186,140],
        "color":[173,161,153,128],
        "score":0.039235652586268537
    },
    {
        "type":2,
        "data":[229,138,254,126,224,148],
        "color":[143,133,134,128],
        "score":0.039210581062797185
    },
    {
        "type":2,
        "data":[58,110,35,119,65,88],
        "color":[22,35,44,128],
        "score":0.039161531042908364
    },
    {
        "type":2,
        "data":[59,26,61,30,76,36],
        "color":[232,216,201,128],
        "score":0.039142356911381064
    },
    {
        "type":2,
        "data":[101,20,122,0,117,20],
        "color":[226,204,187,128],
        "score":0.03912836329789066
    },
    {
        "type":2,
        "data":[29,20,41,25,34,25],
        "color":[198,185,170,128],
        "score":0.039018306625494534
    },
    {
        "type":2,
        "data":[160,121,123,127,170,137],
        "color":[20,12,10,128],
        "score":0.038881868558560066
    },
    {
        "type":2,
        "data":[108,46,78,37,92,23],
        "color":[217,195,183,128],
        "score":0.03884923118313345
    },
    {
        "type":2,
        "data":[7,43,14,45,29,33],
        "color":[153,146,134,128],
        "score":0.038797551047632765
    },
    {
        "type":2,
        "data":[19,104,0,100,0,85],
        "color":[169,158,148,128],
        "score":0.038765656524416596
    },
    {
        "type":2,
        "data":[126,38,109,20,137,39],
        "color":[161,152,143,128],
        "score":0.03872900190222049
    },
    {
        "type":2,
        "data":[110,25,107,9,107,39],
        "color":[215,192,178,128],
        "score":0.03870409934426755
    },
    {
        "type":2,
        "data":[184,86,159,92,188,95],
        "color":[193,178,166,128],
        "score":0.038669451016965874
    },
    {
        "type":2,
        "data":[153,127,157,122,175,136],
        "color":[25,17,13,128],
        "score":0.03864586620347953
    },
    {
        "type":2,
        "data":[27,59,19,95,20,63],
        "color":[60,62,65,128],
        "score":0.038582420378700605
    },
    {
        "type":2,
        "data":[225,119,224,116,230,118],
        "color":[255,255,250,128],
        "score":0.03848282728624775
    },
    {
        "type":2,
        "data":[56,32,41,0,43,23],
        "color":[201,174,156,128],
        "score":0.038446320772090724
    },
    {
        "type":2,
        "data":[150,21,134,48,145,14],
        "color":[213,196,183,128],
        "score":0.03840454413464417
    },
    {
        "type":2,
        "data":[168,29,165,31,177,33],
        "color":[187,163,144,128],
        "score":0.038379371268757304
    },
    {
        "type":2,
        "data":[202,105,236,126,209,114],
        "color":[164,147,143,128],
        "score":0.038327634458663835
    },
    {
        "type":2,
        "data":[67,102,65,79,71,68],
        "color":[129,111,105,128],
        "score":0.03820652131383062
    },
    {
        "type":2,
        "data":[119,21,80,24,88,22],
        "color":[154,127,111,128],
        "score":0.03796057400730915
    },
    {
        "type":2,
        "data":[243,84,206,84,233,105],
        "color":[156,144,139,128],
        "score":0.03794279955946161
    },
    {
        "type":2,
        "data":[106,81,103,73,123,75],
        "color":[121,105,96,128],
        "score":0.03791449247707746
    },
    {
        "type":2,
        "data":[205,105,203,84,232,93],
        "color":[158,144,137,128],
        "score":0.037883989460838506
    },
    {
        "type":2,
        "data":[129,17,127,18,158,0],
        "color":[163,139,125,128],
        "score":0.037755003835111905
    },
    {
        "type":2,
        "data":[0,15,0,18,23,31],
        "color":[111,101,87,128],
        "score":0.037707660188347494
    },
    {
        "type":2,
        "data":[135,46,140,53,108,42],
        "color":[138,123,112,128],
        "score":0.037661169506253415
    },
    {
        "type":2,
        "data":[20,78,64,83,64,94],
        "color":[53,61,68,128],
        "score":0.03763631275312746
    },
    {
        "type":2,
        "data":[184,27,194,25,197,28],
        "color":[175,150,135,128],
        "score":0.03759304646072667
    },
    {
        "type":2,
        "data":[151,114,133,124,134,103],
        "color":[170,159,149,128],
        "score":0.03756979916246536
    },
    {
        "type":2,
        "data":[169,125,179,143,181,142],
        "color":[133,125,122,128],
        "score":0.037517946700623944
    },
    {
        "type":2,
        "data":[4,113,56,131,18,136],
        "color":[124,123,121,128],
        "score":0.03749353185536839
    },
    {
        "type":2,
        "data":[255,74,236,68,255,65],
        "color":[210,202,195,128],
        "score":0.03747246336196894
    },
    {
        "type":2,
        "data":[62,129,104,143,78,143],
        "color":[142,139,134,128],
        "score":0.03743284160518628
    },
    {
        "type":2,
        "data":[161,80,160,44,180,61],
        "color":[204,184,171,128],
        "score":0.03739458494211108
    },
    {
        "type":2,
        "data":[88,78,75,88,113,111],
        "color":[183,169,157,128],
        "score":0.03737851266617962
    },
    {
        "type":2,
        "data":[253,78,215,98,255,91],
        "color":[152,142,136,128],
        "score":0.03733188167609172
    },
    {
        "type":2,
        "data":[228,99,194,132,215,119],
        "color":[155,144,138,128],
        "score":0.037295256669576025
    },
    {
        "type":2,
        "data":[220,133,196,134,208,116],
        "color":[144,135,131,128],
        "score":0.037249466418938296
    },
    {
        "type":2,
        "data":[104,73,109,41,111,64],
        "color":[162,142,125,128],
        "score":0.0372194369588743
    },
    {
        "type":2,
        "data":[248,73,195,106,218,77],
        "color":[166,151,141,128],
        "score":0.037202928785947866
    },
    {
        "type":2,
        "data":[184,88,168,82,200,111],
        "color":[192,174,165,128],
        "score":0.03717678099696801
    },
    {
        "type":2,
        "data":[159,43,188,24,180,65],
        "color":[214,192,179,128],
        "score":0.03716215949819522
    },
    {
        "type":2,
        "data":[65,56,80,15,87,56],
        "color":[210,190,174,128],
        "score":0.037140950768288876
    },
    {
        "type":2,
        "data":[200,111,168,129,211,101],
        "color":[183,166,159,128],
        "score":0.03711760295379361
    },
    {
        "type":2,
        "data":[164,105,186,126,188,117],
        "color":[223,204,198,128],
        "score":0.03707570327117396
    },
    {
        "type":2,
        "data":[253,44,268,56,248,33],
        "color":[147,119,109,128],
        "score":0.037032860629591255
    },
    {
        "type":2,
        "data":[169,128,154,116,183,126],
        "color":[176,162,155,128],
        "score":0.03697960240522972
    },
    {
        "type":2,
        "data":[123,13,136,6,126,18],
        "color":[212,158,130,128],
        "score":0.03694777292859238
    },
    {
        "type":2,
        "data":[255,87,255,82,238,55],
        "color":[187,162,145,128],
        "score":0.036915181458354665
    },
    {
        "type":2,
        "data":[226,112,239,113,209,110],
        "color":[254,242,235,128],
        "score":0.03681503567527625
    },
    {
        "type":2,
        "data":[10,77,0,70,15,72],
        "color":[194,175,161,128],
        "score":0.036803059039000226
    },
    {
        "type":2,
        "data":[111,133,178,143,107,143],
        "color":[2,4,5,128],
        "score":0.03675202043766268
    },
    {
        "type":2,
        "data":[167,121,154,115,178,135],
        "color":[168,154,148,128],
        "score":0.03673767558894064
    },
    {
        "type":2,
        "data":[251,88,236,103,261,81],
        "color":[148,130,122,128],
        "score":0.03672617352573142
    },
    {
        "type":2,
        "data":[156,0,141,6,120,0],
        "color":[227,213,198,128],
        "score":0.03669663240927714
    },
    {
        "type":2,
        "data":[186,129,177,125,179,146],
        "color":[157,146,141,128],
        "score":0.03668454604276173
    },
    {
        "type":2,
        "data":[249,80,244,74,247,72],
        "color":[90,84,76,128],
        "score":0.03658515295865967
    },
    {
        "type":2,
        "data":[145,116,120,109,103,119],
        "color":[170,158,150,128],
        "score":0.036562244645865195
    },
    {
        "type":2,
        "data":[151,117,134,123,105,107],
        "color":[167,155,146,128],
        "score":0.03654458631254752
    },
    {
        "type":2,
        "data":[208,102,226,103,221,97],
        "color":[87,82,82,128],
        "score":0.03647560596454349
    },
    {
        "type":2,
        "data":[222,115,216,98,217,117],
        "color":[158,144,139,128],
        "score":0.03643720867603492
    },
    {
        "type":2,
        "data":[51,28,51,0,28,0],
        "color":[209,183,166,128],
        "score":0.03642114058762018
    },
    {
        "type":2,
        "data":[198,133,182,131,187,121],
        "color":[185,170,164,128],
        "score":0.03638657697753609
    },
    {
        "type":2,
        "data":[28,32,27,51,14,61],
        "color":[211,191,174,128],
        "score":0.03634472840731614
    },
    {
        "type":2,
        "data":[147,106,112,94,139,82],
        "color":[125,110,101,128],
        "score":0.03631944593765746
    },
    {
        "type":2,
        "data":[231,135,197,125,195,134],
        "color":[146,134,131,128],
        "score":0.03628092793654555
    },
    {
        "type":2,
        "data":[175,113,181,124,170,119],
        "color":[179,162,156,128],
        "score":0.03625600370049318
    },
    {
        "type":2,
        "data":[213,0,199,25,181,21],
        "color":[222,198,181,128],
        "score":0.036239073919855015
    },
    {
        "type":2,
        "data":[22,58,0,47,35,47],
        "color":[205,186,169,128],
        "score":0.03617258168036388
    },
    {
        "type":2,
        "data":[201,68,168,79,216,73],
        "color":[207,187,176,128],
        "score":0.03615543110905617
    },
    {
        "type":2,
        "data":[201,120,164,98,196,125],
        "color":[182,166,159,128],
        "score":0.03611686091490422
    },
    {
        "type":2,
        "data":[230,19,255,39,255,37],
        "color":[207,177,155,128],
        "score":0.036102577130465406
    },
    {
        "type":2,
        "data":[6,26,18,37,22,36],
        "color":[142,126,116,128],
        "score":0.03606694629757601
    },
    {
        "type":2,
        "data":[63,76,23,73,28,58],
        "color":[68,74,78,128],
        "score":0.036049910373660045
    },
    {
        "type":2,
        "data":[63,131,91,132,83,147],
        "color":[145,140,134,128],
        "score":0.036040422878451155
    },
    {
        "type":2,
        "data":[160,143,126,126,105,143],
        "color":[5,5,6,128],
        "score":0.03602497540001247
    },
    {
        "type":2,
        "data":[33,53,56,55,54,45],
        "color":[101,93,92,128],
        "score":0.03601584475679477
    },
    {
        "type":2,
        "data":[206,37,213,49,206,52],
        "color":[192,168,153,128],
        "score":0.03600080679611011
    },
    {
        "type":2,
        "data":[117,0,103,12,70,0],
        "color":[230,211,195,128],
        "score":0.03599070796843477
    },
    {
        "type":2,
        "data":[148,77,148,110,162,71],
        "color":[141,124,112,128],
        "score":0.03596834457625616
    },
    {
        "type":2,
        "data":[125,67,121,59,127,71],
        "color":[117,105,97,128],
        "score":0.03595864413634923
    },
    {
        "type":2,
        "data":[240,78,211,83,231,58],
        "color":[177,158,145,128],
        "score":0.03591248116879062
    },
    {
        "type":2,
        "data":[28,5,33,0,29,0],
        "color":[227,209,200,128],
        "score":0.03589761344806529
    },
    {
        "type":2,
        "data":[235,125,242,127,244,132],
        "color":[238,227,223,128],
        "score":0.03577320483046396
    },
    {
        "type":2,
        "data":[214,113,243,127,230,123],
        "color":[157,143,141,128],
        "score":0.03572829831157935
    },
    {
        "type":2,
        "data":[11,75,9,99,0,76],
        "color":[161,143,132,128],
        "score":0.03570564788762965
    },
    {
        "type":2,
        "data":[72,117,40,133,79,117],
        "color":[133,129,128,128],
        "score":0.03569518360410269
    },
    {
        "type":2,
        "data":[22,62,33,50,37,53],
        "color":[114,99,93,128],
        "score":0.035678519722637164
    },
    {
        "type":2,
        "data":[18,94,23,113,62,116],
        "color":[21,35,43,128],
        "score":0.0356517775392948
    },
    {
        "type":2,
        "data":[221,7,224,0,182,0],
        "color":[216,198,188,128],
        "score":0.03564386069657379
    },
    {
        "type":2,
        "data":[87,116,107,119,54,135],
        "color":[162,151,145,128],
        "score":0.035622910321716106
    },
    {
        "type":2,
        "data":[58,50,54,35,64,53],
        "color":[175,147,131,128],
        "score":0.03561015786980576
    },
    {
        "type":2,
        "data":[62,123,71,116,101,103],
        "color":[148,138,134,128],
        "score":0.035577774526574006
    },
    {
        "type":2,
        "data":[15,0,22,16,52,9],
        "color":[214,187,168,128],
        "score":0.03556477275792268
    },
    {
        "type":2,
        "data":[228,57,241,80,233,61],
        "color":[181,158,146,128],
        "score":0.03555871957489587
    },
    {
        "type":2,
        "data":[121,49,134,49,158,92],
        "color":[132,117,106,128],
        "score":0.035546133339498936
    },
    {
        "type":2,
        "data":[49,143,0,117,1,136],
        "color":[116,116,115,128],
        "score":0.035530139267601665
    },
    {
        "type":2,
        "data":[205,101,216,101,192,96],
        "color":[154,138,130,128],
        "score":0.03549527659272169
    },
    {
        "type":2,
        "data":[54,20,112,20,83,0],
        "color":[223,202,185,128],
        "score":0.03547481322825699
    },
    {
        "type":2,
        "data":[133,35,129,44,123,41],
        "color":[119,114,107,128],
        "score":0.035445660658006854
    },
    {
        "type":2,
        "data":[211,133,220,143,221,143],
        "color":[255,245,241,128],
        "score":0.03538289775964299
    },
    {
        "type":2,
        "data":[11,47,42,33,26,36],
        "color":[202,189,175,128],
        "score":0.03535768854896731
    },
    {
        "type":2,
        "data":[127,67,126,76,124,77],
        "color":[118,106,99,128],
        "score":0.035334409469888715
    },
    {
        "type":2,
        "data":[55,46,31,43,47,27],
        "color":[118,115,104,128],
        "score":0.0353097386582704
    },
    {
        "type":2,
        "data":[17,113,1,121,53,143],
        "color":[128,126,122,128],
        "score":0.03529749650740915
    },
    {
        "type":2,
        "data":[58,39,32,38,29,41],
        "color":[120,114,101,128],
        "score":0.03526133906133137
    },
    {
        "type":2,
        "data":[152,95,150,109,149,104],
        "color":[164,144,135,128],
        "score":0.035241222244142084
    },
    {
        "type":2,
        "data":[165,97,181,102,178,105],
        "color":[229,211,204,128],
        "score":0.035229927297172385
    },
    {
        "type":2,
        "data":[245,143,243,119,255,105],
        "color":[131,127,123,128],
        "score":0.03520137335451094
    },
    {
        "type":2,
        "data":[225,132,238,114,251,105],
        "color":[153,144,143,128],
        "score":0.035184991363440006
    },
    {
        "type":2,
        "data":[107,113,115,88,110,101],
        "color":[117,100,90,128],
        "score":0.03513206376150161
    },
    {
        "type":2,
        "data":[210,54,252,46,217,65],
        "color":[225,215,208,128],
        "score":0.03511329711746839
    },
    {
        "type":2,
        "data":[161,0,157,6,194,0],
        "color":[232,212,199,128],
        "score":0.03510081857835693
    },
    {
        "type":2,
        "data":[133,124,145,123,107,140],
        "color":[11,8,6,128],
        "score":0.03507472720354847
    },
    {
        "type":2,
        "data":[161,21,156,19,158,29],
        "color":[236,224,210,128],
        "score":0.03506041894310678
    },
    {
        "type":2,
        "data":[184,106,192,114,181,96],
        "color":[239,222,216,128],
        "score":0.03502963535059675
    },
    {
        "type":2,
        "data":[166,96,177,99,162,100],
        "color":[194,177,167,128],
        "score":0.0350176511850025
    },
    {
        "type":2,
        "data":[158,135,155,136,152,113],
        "color":[16,9,8,128],
        "score":0.03488537427349793
    },
    {
        "type":2,
        "data":[205,72,216,66,211,81],
        "color":[204,185,175,128],
        "score":0.03486752625067021
    },
    {
        "type":2,
        "data":[249,134,223,130,240,129],
        "color":[144,131,129,128],
        "score":0.034825697053716645
    },
    {
        "type":2,
        "data":[0,115,0,88,1,107],
        "color":[139,129,124,128],
        "score":0.03481264358304011
    },
    {
        "type":2,
        "data":[29,121,21,111,38,120],
        "color":[2,13,15,128],
        "score":0.03472867947454881
    },
    {
        "type":2,
        "data":[212,50,219,72,235,51],
        "color":[228,217,209,128],
        "score":0.034689494019136874
    },
    {
        "type":2,
        "data":[158,140,173,131,174,143],
        "color":[15,10,12,128],
        "score":0.03466843621082608
    },
    {
        "type":2,
        "data":[144,35,159,40,139,27],
        "color":[204,183,173,128],
        "score":0.03466098833338815
    },
    {
        "type":2,
        "data":[183,107,199,107,175,112],
        "color":[187,170,163,128],
        "score":0.0346327272017609
    },
    {
        "type":2,
        "data":[215,133,182,141,199,129],
        "color":[140,132,127,128],
        "score":0.0346079449358232
    },
    {
        "type":2,
        "data":[32,23,53,43,24,29],
        "color":[120,115,103,128],
        "score":0.034565059362326706
    },
    {
        "type":2,
        "data":[126,5,136,-5,137,-11],
        "color":[232,214,199,128],
        "score":0.034551145255584406
    },
    {
        "type":2,
        "data":[205,84,247,77,249,86],
        "color":[166,152,144,128],
        "score":0.034538871263045695
    },
    {
        "type":2,
        "data":[78,52,67,67,99,71],
        "color":[199,178,166,128],
        "score":0.034522277608583
    },
    {
        "type":2,
        "data":[161,75,162,91,154,52],
        "color":[152,132,123,128],
        "score":0.03447837348761218
    },
    {
        "type":2,
        "data":[217,52,230,46,225,44],
        "color":[249,241,231,128],
        "score":0.03446179912456265
    },
    {
        "type":2,
        "data":[255,122,220,159,232,140],
        "color":[129,125,124,128],
        "score":0.03444988837652029
    },
    {
        "type":2,
        "data":[228,137,224,139,231,122],
        "color":[143,133,133,128],
        "score":0.034416561807765415
    },
    {
        "type":2,
        "data":[255,130,242,143,255,143],
        "color":[107,107,107,128],
        "score":0.03440448382946593
    },
    {
        "type":2,
        "data":[116,129,123,115,125,125],
        "color":[158,146,142,128],
        "score":0.03439111582369477
    },
    {
        "type":2,
        "data":[59,10,34,5,55,0],
        "color":[218,191,173,128],
        "score":0.034383864182801455
    },
    {
        "type":2,
        "data":[213,143,219,139,214,139],
        "color":[168,143,144,128],
        "score":0.03435690354015649
    },
    {
        "type":2,
        "data":[106,46,82,63,103,63],
        "color":[199,179,167,128],
        "score":0.03434154609139761
    },
    {
        "type":2,
        "data":[230,108,214,128,219,122],
        "color":[223,205,201,128],
        "score":0.03431903948747102
    },
    {
        "type":2,
        "data":[9,25,0,21,0,39],
        "color":[180,153,135,128],
        "score":0.03427846845510151
    },
    {
        "type":2,
        "data":[39,52,59,58,23,62],
        "color":[88,87,88,128],
        "score":0.03426560676213323
    },
    {
        "type":2,
        "data":[90,47,92,41,91,55],
        "color":[169,148,135,128],
        "score":0.03424465223828472
    },
    {
        "type":2,
        "data":[237,106,238,117,255,106],
        "color":[158,145,141,128],
        "score":0.034231931697072865
    },
    {
        "type":2,
        "data":[66,53,72,73,75,63],
        "color":[190,170,157,128],
        "score":0.0342137976687441
    },
    {
        "type":2,
        "data":[124,109,135,100,110,107],
        "color":[113,98,88,128],
        "score":0.0341860302201942
    },
    {
        "type":2,
        "data":[200,93,212,104,215,88],
        "color":[162,147,140,128],
        "score":0.03416808854905348
    },
    {
        "type":2,
        "data":[71,53,80,94,71,87],
        "color":[195,175,163,128],
        "score":0.03414004411708759
    },
    {
        "type":2,
        "data":[209,82,182,93,167,82],
        "color":[199,180,169,128],
        "score":0.03412744196886001
    },
    {
        "type":2,
        "data":[10,62,10,70,20,68],
        "color":[144,142,132,128],
        "score":0.0341052221941073
    },
    {
        "type":2,
        "data":[23,16,33,18,25,10],
        "color":[215,198,177,128],
        "score":0.03409516450527595
    },
    {
        "type":2,
        "data":[147,120,156,121,136,125],
        "color":[23,17,7,128],
        "score":0.0340782216711383
    },
    {
        "type":2,
        "data":[255,0,243,0,254,40],
        "color":[193,167,150,128],
        "score":0.03406747026882417
    },
    {
        "type":2,
        "data":[149,131,110,135,114,130],
        "color":[6,5,6,128],
        "score":0.03403598779233852
    },
    {
        "type":2,
        "data":[192,9,203,17,197,20],
        "color":[214,189,174,128],
        "score":0.03402995382374555
    },
    {
        "type":2,
        "data":[82,59,84,56,104,54],
        "color":[192,172,158,128],
        "score":0.03402431114108124
    },
    {
        "type":2,
        "data":[54,22,85,30,74,15],
        "color":[219,197,180,128],
        "score":0.03401657353555713
    },
    {
        "type":2,
        "data":[150,40,163,74,158,29],
        "color":[208,189,177,128],
        "score":0.033987256446968574
    },
    {
        "type":2,
        "data":[2,52,30,38,8,66],
        "color":[204,185,169,128],
        "score":0.0339760112154923
    },
    {
        "type":2,
        "data":[233,135,190,124,230,142],
        "color":[152,139,138,128],
        "score":0.033949683616851
    },
    {
        "type":2,
        "data":[164,29,154,57,161,19],
        "color":[214,193,179,128],
        "score":0.03394336238475827
    },
    {
        "type":2,
        "data":[16,24,11,0,24,0],
        "color":[204,177,159,128],
        "score":0.0339344722644109
    }
]